{
  "name": "dais v0.15 Mastodon-family federation lab",
  "updated": "2026-06-15",
  "targets": [
    {
      "server": "mastodon",
      "name": "Mastodon / mastodon.social live account",
      "capabilities": {
        "webfinger": {
          "status": "pass",
          "detail": "Covered by the ActivityPub and federation-matrix Rust conformance gates."
        },
        "actor": {
          "status": "pass",
          "detail": "Actor shape, locked posture, and publicKey covered by conformance."
        },
        "follow": {
          "status": "pass",
          "detail": "Live Mastodon follow flow covered by toot smoke path."
        },
        "accept": {
          "status": "pass",
          "detail": "Approved followers receive signed Accept delivery."
        },
        "create": {
          "status": "pass",
          "detail": "Followers-only and public Create delivery covered by live smoke path."
        },
        "update": {
          "status": "pass",
          "detail": "Core inbox regressions cover Mastodon-style Update(Note) and Update(Question) modifying stored timeline rows."
        },
        "delete": {
          "status": "pass",
          "detail": "Core inbox regression covers Mastodon-style Delete(Note) removing stored timeline rows."
        },
        "reply": {
          "status": "pass",
          "detail": "Covered by the live toot inbound reply smoke gate, owner post-detail assertion, and followed-actor reply timeline regression."
        },
        "like": {
          "status": "pass",
          "detail": "Covered by the live toot favourite smoke gate and owner post-detail assertion."
        },
        "announce": {
          "status": "pass",
          "detail": "Covered by core inbox Announce/Undo regression tests for Mastodon-style boosts."
        },
        "undo": {
          "status": "pass",
          "detail": "Core inbox regression covers Undo of Like and Announce interactions."
        },
        "idempotency": {
          "status": "pass",
          "detail": "Follower and following writes use conflict-safe upserts; inbox interaction regressions verify stable object state after Undo cleanup."
        },
        "content_shape": {
          "status": "pass",
          "detail": "ActivityPub conformance, Mastodon API conformance, and core inbox regressions cover Note basics, replies/likes/shares, media attachments, mentions, hashtags, and Question/poll rendering and ingestion."
        },
        "authorized_fetch": {
          "status": "pass",
          "detail": "Anonymous private object denial and signed-fetch helper covered by conformance."
        },
        "follower_synchronization": {
          "status": "pass",
          "detail": "MASTODON-SYNC-01 covers signed partial follower synchronization collection fetches for followers-only delivery support."
        },
        "private_visibility": {
          "status": "pass",
          "detail": "Anonymous outbox/object checks prevent private and E2EE leakage."
        }
      }
    },
    {
      "server": "pleroma",
      "name": "Pleroma/Akkoma local or tunnel target",
      "capabilities": {
        "webfinger": {
          "status": "manual",
          "detail": "Run federation-matrix with DAIS_FEDERATION_TARGETS containing a Pleroma/Akkoma account."
        },
        "actor": {
          "status": "manual",
          "detail": "Remote actor shape is probed when actor URL is configured."
        },
        "follow": {
          "status": "manual",
          "detail": "Run from a local/tunnel Pleroma account and verify pending follower row."
        },
        "accept": {
          "status": "manual",
          "detail": "Approve from dais CLI/TUI and verify remote follow state."
        },
        "create": {
          "status": "manual",
          "detail": "Deliver public and followers-only Create to approved Pleroma follower."
        },
        "update": {
          "status": "manual",
          "detail": "Update a Pleroma-visible Note and verify the remote timeline/rendered object changes."
        },
        "delete": {
          "status": "manual",
          "detail": "Delete a Pleroma-visible Note and verify the remote tombstone/delete state."
        },
        "reply": {
          "status": "manual",
          "detail": "Reply from Pleroma and verify inbox ingestion."
        },
        "like": {
          "status": "manual",
          "detail": "Favourite from Pleroma and verify Like ingestion."
        },
        "announce": {
          "status": "manual",
          "detail": "Repeat from Pleroma and verify Announce ingestion."
        },
        "undo": {
          "status": "manual",
          "detail": "Undo a Pleroma favourite/announce and verify local interaction cleanup."
        },
        "idempotency": {
          "status": "manual",
          "detail": "Replay duplicate Pleroma activities and verify local rows remain idempotent."
        },
        "content_shape": {
          "status": "manual",
          "detail": "Verify Pleroma rendering for mentions, hashtags, media attachments, and Question/poll objects."
        },
        "authorized_fetch": {
          "status": "manual",
          "detail": "Verify followers-only dereference from approved actor and anonymous denial."
        },
        "follower_synchronization": {
          "status": "manual",
          "detail": "If the target supports Mastodon-compatible followers-only sync, verify Collection-Synchronization delivery headers and signed partial collection fetches."
        },
        "private_visibility": {
          "status": "pass",
          "detail": "Dais-side anonymous privacy gate is server-independent."
        }
      }
    },
    {
      "server": "misskey",
      "name": "Misskey/Firefish local or tunnel target",
      "capabilities": {
        "webfinger": {
          "status": "manual",
          "detail": "Run federation-matrix with DAIS_FEDERATION_TARGETS containing a Misskey account."
        },
        "actor": {
          "status": "manual",
          "detail": "Remote actor shape is probed when actor URL is configured."
        },
        "follow": {
          "status": "manual",
          "detail": "Follow from Misskey and verify dais pending follower row."
        },
        "accept": {
          "status": "manual",
          "detail": "Approve from dais and verify Misskey follow state."
        },
        "create": {
          "status": "manual",
          "detail": "Deliver Create and inspect Misskey timeline rendering."
        },
        "update": {
          "status": "manual",
          "detail": "Update a Misskey-visible Note and verify rendered object/timeline changes."
        },
        "delete": {
          "status": "manual",
          "detail": "Delete a Misskey-visible Note and verify remote deletion/tombstone behavior."
        },
        "reply": {
          "status": "manual",
          "detail": "Reply from Misskey and verify inbox ingestion."
        },
        "like": {
          "status": "manual",
          "detail": "React/like from Misskey and verify compatible ActivityPub ingestion."
        },
        "announce": {
          "status": "manual",
          "detail": "Renote from Misskey and verify Announce-compatible ingestion."
        },
        "undo": {
          "status": "manual",
          "detail": "Undo Misskey reaction/renote activity where exposed and verify local cleanup."
        },
        "idempotency": {
          "status": "manual",
          "detail": "Replay duplicate Misskey activities and verify local rows remain idempotent."
        },
        "content_shape": {
          "status": "manual",
          "detail": "Verify Misskey rendering for mentions, hashtags, media attachments, polls, and quote-related extensions where present."
        },
        "authorized_fetch": {
          "status": "manual",
          "detail": "Verify followers-only object access with signed fetch where Misskey supports it."
        },
        "follower_synchronization": {
          "status": "manual",
          "detail": "Verify whether Misskey-compatible targets consume Mastodon Collection-Synchronization headers or ignore them safely."
        },
        "private_visibility": {
          "status": "pass",
          "detail": "Dais-side anonymous privacy gate is server-independent."
        }
      }
    },
    {
      "server": "pixelfed",
      "name": "Pixelfed local or tunnel target",
      "capabilities": {
        "webfinger": {
          "status": "manual",
          "detail": "Run federation-matrix with DAIS_FEDERATION_TARGETS containing a Pixelfed account."
        },
        "actor": {
          "status": "manual",
          "detail": "Remote actor shape is probed when actor URL is configured."
        },
        "follow": {
          "status": "manual",
          "detail": "Follow from Pixelfed and verify dais pending follower row."
        },
        "accept": {
          "status": "manual",
          "detail": "Approve from dais and verify Pixelfed follow state."
        },
        "create": {
          "status": "manual",
          "detail": "Deliver Note fallback; media-specific rendering belongs to later media work."
        },
        "update": {
          "status": "manual",
          "detail": "Update a Pixelfed-visible Note/media post and verify rendered object changes where supported."
        },
        "delete": {
          "status": "manual",
          "detail": "Delete a Pixelfed-visible Note/media post and verify remote deletion behavior."
        },
        "reply": {
          "status": "manual",
          "detail": "Reply/comment from Pixelfed and verify inbox ingestion."
        },
        "like": {
          "status": "manual",
          "detail": "Like from Pixelfed and verify Like ingestion."
        },
        "announce": {
          "status": "manual",
          "detail": "Pixelfed boost/share behavior varies; record observed behavior as compatibility data."
        },
        "undo": {
          "status": "manual",
          "detail": "Undo Pixelfed like/share behavior where exposed and verify local cleanup."
        },
        "idempotency": {
          "status": "manual",
          "detail": "Replay duplicate Pixelfed activities and verify local rows remain idempotent."
        },
        "content_shape": {
          "status": "manual",
          "detail": "Verify Pixelfed rendering for image/video attachments, captions, mentions, hashtags, and Note fallback behavior."
        },
        "authorized_fetch": {
          "status": "manual",
          "detail": "Verify followers-only object access where Pixelfed supports signed fetch."
        },
        "follower_synchronization": {
          "status": "manual",
          "detail": "Verify whether Pixelfed-compatible targets consume Mastodon Collection-Synchronization headers or ignore them safely."
        },
        "private_visibility": {
          "status": "pass",
          "detail": "Dais-side anonymous privacy gate is server-independent."
        }
      }
    }
  ]
}
